DankCord/DankCord.py
DankCord/Objects.py
DankCord/__init__.py
DankCord/api.py
DankCord/core.py
DankCord/exceptions.py
DankCord/gateway.py
DankCord-0.0.2.5.dist-info/METADATA
DankCord-0.0.2.5.dist-info/WHEEL
DankCord-0.0.2.5.dist-info/top_level.txt
DankCord-0.0.2.5.dist-info/RECORD
