Metadata-Version: 2.1
Name: DankCord
Version: 0.0.2.5
Summary: The first python library for Dank Memer selfbots. Incredibly fast, secure, strong, and reliable.
Author-email: sxvxge69@gmail.com, contact@privatepanda.co
Maintainer-email: sxvxge69@gmail.com, contact@privatepanda.co
License: MIT
Keywords: bot,automation,discord,discord-bot,dank-memer,dankmemer,dank-memer-farm,dank-memer-farmer,dank-memer-coins,dank-memer-coins-farmer
